sms-spam-detection/__init__.py
sms-spam-detection/app.py
sms-spam-detection/test.py
sms_spam_detection/__init__.py
sms_spam_detection/app.py
sms_spam_detection/best_extra_trees_model.pkl
sms_spam_detection/best_logistic_regression_model.pkl
sms_spam_detection/test.py
sms_spam_detection/word2vec.model
sms_spam_detection-0.1.6.dist-info/LICENSE
sms_spam_detection-0.1.6.dist-info/METADATA
sms_spam_detection-0.1.6.dist-info/WHEEL
sms_spam_detection-0.1.6.dist-info/top_level.txt
sms_spam_detection-0.1.6.dist-info/RECORD
