Metadata-Version: 2.1
Name: sms_spam_detection
Version: 0.1.6
Summary: A Python package for SMS spam detection.
License-File: LICENSE
Requires-Dist: blinker==1.9.0
Requires-Dist: click==8.1.8
Requires-Dist: Cython==3.0.11
Requires-Dist: gensim==4.3.1
Requires-Dist: itsdangerous==2.2.0
Requires-Dist: Jinja2==3.1.5
Requires-Dist: joblib==1.4.2
Requires-Dist: MarkupSafe==3.0.2
Requires-Dist: nltk==3.8.1
Requires-Dist: numpy==1.24.3
Requires-Dist: pytz==2024.2
Requires-Dist: regex==2024.11.6
Requires-Dist: scikit-learn==1.3.1
Requires-Dist: scipy==1.10.1
Requires-Dist: smart-open==7.1.0
Requires-Dist: threadpoolctl==3.5.0
Requires-Dist: tqdm==4.67.1
Requires-Dist: tzdata==2024.2
Requires-Dist: Werkzeug==3.1.3
Requires-Dist: wrapt==1.17.0
Requires-Dist: waitress
